mongo_connect/__init__.py
mongo_connect/mongo_crud.py
mongoconnectx576pkg-0.0.4.dist-info/LICENSE
mongoconnectx576pkg-0.0.4.dist-info/METADATA
mongoconnectx576pkg-0.0.4.dist-info/WHEEL
mongoconnectx576pkg-0.0.4.dist-info/top_level.txt
mongoconnectx576pkg-0.0.4.dist-info/RECORD
